msldap/__init__.py
msldap/__main__.py
msldap/_version.py
msldap/bloodhound.py
msldap/client.py
msldap/connection.py
msldap/commons/__init__.py
msldap/commons/adexplorer.py
msldap/commons/authbuilder.py
msldap/commons/common.py
msldap/commons/exceptions.py
msldap/commons/factory.py
msldap/commons/ldif.py
msldap/commons/plugin.py
msldap/commons/target.py
msldap/commons/utils.py
msldap/examples/__init__.py
msldap/examples/jsontest.py
msldap/examples/msldapbloodhound.py
msldap/examples/msldapclient.py
msldap/examples/msldapcompdnslist.py
msldap/examples/utils/__init__.py
msldap/examples/utils/completers.py
msldap/external/__init__.py
msldap/external/aiocmd/__init__.py
msldap/external/aiocmd/setup.py
msldap/external/aiocmd/aiocmd/__init__.py
msldap/external/aiocmd/aiocmd/aiocmd.py
msldap/external/aiocmd/aiocmd/nested_completer.py
msldap/external/asciitree/__init__.py
msldap/external/asciitree/setup.py
msldap/external/asciitree/asciitree/__init__.py
msldap/external/asciitree/asciitree/drawing.py
msldap/external/asciitree/asciitree/traversal.py
msldap/external/asciitree/asciitree/util.py
msldap/external/bloodhoundpy/__init__.py
msldap/external/bloodhoundpy/acls.py
msldap/external/bloodhoundpy/resolver.py
msldap/external/bloodhoundpy/utils.py
msldap/external/bloodhoundpy/lib/__init__.py
msldap/external/bloodhoundpy/lib/cstruct.py
msldap/ldap_objects/__init__.py
msldap/ldap_objects/adca.py
msldap/ldap_objects/adcertificatetemplate.py
msldap/ldap_objects/adcomp.py
msldap/ldap_objects/adcontainer.py
msldap/ldap_objects/adenrollmentservice.py
msldap/ldap_objects/adgmsa.py
msldap/ldap_objects/adgpo.py
msldap/ldap_objects/adgroup.py
msldap/ldap_objects/adinfo.py
msldap/ldap_objects/adou.py
msldap/ldap_objects/adschemaentry.py
msldap/ldap_objects/adsec.py
msldap/ldap_objects/adtrust.py
msldap/ldap_objects/aduser.py
msldap/ldap_objects/common.py
msldap/network/__init__.py
msldap/network/packetizer.py
msldap/protocol/__init__.py
msldap/protocol/constants.py
msldap_bad-0.5.26.dist-info/licenses/LICENSE
msldap_bad-0.5.26.dist-info/METADATA
msldap_bad-0.5.26.dist-info/WHEEL
msldap_bad-0.5.26.dist-info/entry_points.txt
msldap_bad-0.5.26.dist-info/top_level.txt
msldap_bad-0.5.26.dist-info/RECORD
