Metadata-Version: 2.4
Name: msldap-bAD
Version: 0.5.26
Summary: Python library to play with MS LDAP
Home-page: https://github.com/CravateRouge/msldap-bAD
Author: Tamas Jos
Author-email: info@skelsecprojects.com
Maintainer: Baptiste Crépin
Maintainer-email: baptiste@cravaterouge.com
Classifier: Programming Language :: Python :: 3.7
Classifier: Programming Language :: Python :: 3.8
Classifier: License :: OSI Approved :: MIT License
Classifier: Operating System :: OS Independent
Requires-Python: >=3.7
License-File: LICENSE
Requires-Dist: unicrypto>=0.0.10
Requires-Dist: asyauth-bAD>=0.0.29
Requires-Dist: asysocks>=0.2.11
Requires-Dist: asn1crypto>=1.3.0
Requires-Dist: winacl>=0.1.8
Requires-Dist: prompt-toolkit>=3.0.2
Requires-Dist: tqdm
Requires-Dist: wcwidth
Requires-Dist: tabulate
Dynamic: author
Dynamic: author-email
Dynamic: classifier
Dynamic: description
Dynamic: home-page
Dynamic: license-file
Dynamic: maintainer
Dynamic: maintainer-email
Dynamic: requires-dist
Dynamic: requires-python
Dynamic: summary
